<?xml version="1.0" encoding="UTF-8" standalone="no"?><?xml-stylesheet type="text/xsl" href="../lib/xsl/lexan.xsl"?><lexan><term lexeme="fun" token="FUNCTION"><location begcolumn="1" begline="1" endcolumn="3" endline="1" loc="1.1 - 1.3"/></term><term lexeme="putChar" token="IDENTIFIER"><location begcolumn="5" begline="1" endcolumn="11" endline="1" loc="1.5 - 1.11"/></term><term lexeme="(" token="LEFTBRAC"><location begcolumn="12" begline="1" endcolumn="12" endline="1" loc="1.12 - 1.12"/></term><term lexeme="c" token="IDENTIFIER"><location begcolumn="13" begline="1" endcolumn="13" endline="1" loc="1.13 - 1.13"/></term><term lexeme=":" token="COL"><location begcolumn="14" begline="1" endcolumn="14" endline="1" loc="1.14 - 1.14"/></term><term lexeme="char" token="CHAR"><location begcolumn="15" begline="1" endcolumn="18" endline="1" loc="1.15 - 1.18"/></term><term lexeme=")" token="RIGHTBRAC"><location begcolumn="19" begline="1" endcolumn="19" endline="1" loc="1.19 - 1.19"/></term><term lexeme=":" token="COL"><location begcolumn="20" begline="1" endcolumn="20" endline="1" loc="1.20 - 1.20"/></term><term lexeme="void" token="VOID"><location begcolumn="21" begline="1" endcolumn="24" endline="1" loc="1.21 - 1.24"/></term><term lexeme="=" token="ASIGN"><location begcolumn="26" begline="1" endcolumn="26" endline="1" loc="1.26 - 1.26"/></term><term lexeme="none" token="NONE"><location begcolumn="28" begline="1" endcolumn="31" endline="1" loc="1.28 - 1.31"/></term><term lexeme="fun" token="FUNCTION"><location begcolumn="1" begline="2" endcolumn="3" endline="2" loc="2.1 - 2.3"/></term><term lexeme="getChar" token="IDENTIFIER"><location begcolumn="5" begline="2" endcolumn="11" endline="2" loc="2.5 - 2.11"/></term><term lexeme="(" token="LEFTBRAC"><location begcolumn="12" begline="2" endcolumn="12" endline="2" loc="2.12 - 2.12"/></term><term lexeme=")" token="RIGHTBRAC"><location begcolumn="13" begline="2" endcolumn="13" endline="2" loc="2.13 - 2.13"/></term><term lexeme=":" token="COL"><location begcolumn="14" begline="2" endcolumn="14" endline="2" loc="2.14 - 2.14"/></term><term lexeme="char" token="CHAR"><location begcolumn="15" begline="2" endcolumn="18" endline="2" loc="2.15 - 2.18"/></term><term lexeme="=" token="ASIGN"><location begcolumn="20" begline="2" endcolumn="20" endline="2" loc="2.20 - 2.20"/></term><term lexeme="(" token="LEFTBRAC"><location begcolumn="22" begline="2" endcolumn="22" endline="2" loc="2.22 - 2.22"/></term><term lexeme="0" token="INTCONST"><location begcolumn="23" begline="2" endcolumn="23" endline="2" loc="2.23 - 2.23"/></term><term lexeme=":" token="COL"><location begcolumn="24" begline="2" endcolumn="24" endline="2" loc="2.24 - 2.24"/></term><term lexeme="char" token="CHAR"><location begcolumn="25" begline="2" endcolumn="28" endline="2" loc="2.25 - 2.28"/></term><term lexeme=")" token="RIGHTBRAC"><location begcolumn="29" begline="2" endcolumn="29" endline="2" loc="2.29 - 2.29"/></term><term lexeme="fun" token="FUNCTION"><location begcolumn="1" begline="3" endcolumn="3" endline="3" loc="3.1 - 3.3"/></term><term lexeme="putInteger" token="IDENTIFIER"><location begcolumn="5" begline="3" endcolumn="14" endline="3" loc="3.5 - 3.14"/></term><term lexeme="(" token="LEFTBRAC"><location begcolumn="15" begline="3" endcolumn="15" endline="3" loc="3.15 - 3.15"/></term><term lexeme="i" token="IDENTIFIER"><location begcolumn="16" begline="3" endcolumn="16" endline="3" loc="3.16 - 3.16"/></term><term lexeme=":" token="COL"><location begcolumn="17" begline="3" endcolumn="17" endline="3" loc="3.17 - 3.17"/></term><term lexeme="integer" token="INTEGER"><location begcolumn="18" begline="3" endcolumn="24" endline="3" loc="3.18 - 3.24"/></term><term lexeme=")" token="RIGHTBRAC"><location begcolumn="25" begline="3" endcolumn="25" endline="3" loc="3.25 - 3.25"/></term><term lexeme=":" token="COL"><location begcolumn="26" begline="3" endcolumn="26" endline="3" loc="3.26 - 3.26"/></term><term lexeme="void" token="VOID"><location begcolumn="27" begline="3" endcolumn="30" endline="3" loc="3.27 - 3.30"/></term><term lexeme="=" token="ASIGN"><location begcolumn="32" begline="3" endcolumn="32" endline="3" loc="3.32 - 3.32"/></term><term lexeme="{" token="LEFTCURL"><location begcolumn="5" begline="4" endcolumn="5" endline="4" loc="4.5 - 4.5"/></term><term lexeme="if" token="IF"><location begcolumn="7" begline="5" endcolumn="8" endline="5" loc="5.7 - 5.8"/></term><term lexeme="(" token="LEFTBRAC"><location begcolumn="10" begline="5" endcolumn="10" endline="5" loc="5.10 - 5.10"/></term><term lexeme="i" token="IDENTIFIER"><location begcolumn="11" begline="5" endcolumn="11" endline="5" loc="5.11 - 5.11"/></term><term lexeme="&lt;" token="LT"><location begcolumn="12" begline="5" endcolumn="12" endline="5" loc="5.12 - 5.12"/></term><term lexeme="0" token="INTCONST"><location begcolumn="13" begline="5" endcolumn="13" endline="5" loc="5.13 - 5.13"/></term><term lexeme=")" token="RIGHTBRAC"><location begcolumn="14" begline="5" endcolumn="14" endline="5" loc="5.14 - 5.14"/></term><term lexeme="then" token="THEN"><location begcolumn="16" begline="5" endcolumn="19" endline="5" loc="5.16 - 5.19"/></term><term lexeme="{" token="LEFTCURL"><location begcolumn="21" begline="5" endcolumn="21" endline="5" loc="5.21 - 5.21"/></term><term lexeme="putChar" token="IDENTIFIER"><location begcolumn="23" begline="5" endcolumn="29" endline="5" loc="5.23 - 5.29"/></term><term lexeme="(" token="LEFTBRAC"><location begcolumn="30" begline="5" endcolumn="30" endline="5" loc="5.30 - 5.30"/></term><term lexeme="'-'" token="CHARACTERCONST"><location begcolumn="31" begline="5" endcolumn="33" endline="5" loc="5.31 - 5.33"/></term><term lexeme=")" token="RIGHTBRAC"><location begcolumn="34" begline="5" endcolumn="34" endline="5" loc="5.34 - 5.34"/></term><term lexeme=";" token="SEMCOL"><location begcolumn="35" begline="5" endcolumn="35" endline="5" loc="5.35 - 5.35"/></term><term lexeme="i" token="IDENTIFIER"><location begcolumn="37" begline="5" endcolumn="37" endline="5" loc="5.37 - 5.37"/></term><term lexeme="=" token="ASIGN"><location begcolumn="38" begline="5" endcolumn="38" endline="5" loc="5.38 - 5.38"/></term><term lexeme="-" token="MINUS"><location begcolumn="39" begline="5" endcolumn="39" endline="5" loc="5.39 - 5.39"/></term><term lexeme="i" token="IDENTIFIER"><location begcolumn="40" begline="5" endcolumn="40" endline="5" loc="5.40 - 5.40"/></term><term lexeme=";" token="SEMCOL"><location begcolumn="41" begline="5" endcolumn="41" endline="5" loc="5.41 - 5.41"/></term><term lexeme="}" token="RIGHTCURL"><location begcolumn="43" begline="5" endcolumn="43" endline="5" loc="5.43 - 5.43"/></term><term lexeme="else" token="ELSE"><location begcolumn="45" begline="5" endcolumn="48" endline="5" loc="5.45 - 5.48"/></term><term lexeme="none" token="NONE"><location begcolumn="50" begline="5" endcolumn="53" endline="5" loc="5.50 - 5.53"/></term><term lexeme=";" token="SEMCOL"><location begcolumn="54" begline="5" endcolumn="54" endline="5" loc="5.54 - 5.54"/></term><term lexeme="if" token="IF"><location begcolumn="7" begline="6" endcolumn="8" endline="6" loc="6.7 - 6.8"/></term><term lexeme="(" token="LEFTBRAC"><location begcolumn="10" begline="6" endcolumn="10" endline="6" loc="6.10 - 6.10"/></term><term lexeme="i" token="IDENTIFIER"><location begcolumn="11" begline="6" endcolumn="11" endline="6" loc="6.11 - 6.11"/></term><term lexeme="==" token="EQL"><location begcolumn="12" begline="6" endcolumn="13" endline="6" loc="6.12 - 6.13"/></term><term lexeme="0" token="INTCONST"><location begcolumn="14" begline="6" endcolumn="14" endline="6" loc="6.14 - 6.14"/></term><term lexeme=")" token="RIGHTBRAC"><location begcolumn="15" begline="6" endcolumn="15" endline="6" loc="6.15 - 6.15"/></term><term lexeme="then" token="THEN"><location begcolumn="17" begline="6" endcolumn="20" endline="6" loc="6.17 - 6.20"/></term><term lexeme="putChar" token="IDENTIFIER"><location begcolumn="22" begline="6" endcolumn="28" endline="6" loc="6.22 - 6.28"/></term><term lexeme="(" token="LEFTBRAC"><location begcolumn="29" begline="6" endcolumn="29" endline="6" loc="6.29 - 6.29"/></term><term lexeme="'0'" token="CHARACTERCONST"><location begcolumn="30" begline="6" endcolumn="32" endline="6" loc="6.30 - 6.32"/></term><term lexeme=")" token="RIGHTBRAC"><location begcolumn="33" begline="6" endcolumn="33" endline="6" loc="6.33 - 6.33"/></term><term lexeme="else" token="ELSE"><location begcolumn="35" begline="6" endcolumn="38" endline="6" loc="6.35 - 6.38"/></term><term lexeme="put" token="IDENTIFIER"><location begcolumn="40" begline="6" endcolumn="42" endline="6" loc="6.40 - 6.42"/></term><term lexeme="(" token="LEFTBRAC"><location begcolumn="43" begline="6" endcolumn="43" endline="6" loc="6.43 - 6.43"/></term><term lexeme="i" token="IDENTIFIER"><location begcolumn="44" begline="6" endcolumn="44" endline="6" loc="6.44 - 6.44"/></term><term lexeme=")" token="RIGHTBRAC"><location begcolumn="45" begline="6" endcolumn="45" endline="6" loc="6.45 - 6.45"/></term><term lexeme=";" token="SEMCOL"><location begcolumn="46" begline="6" endcolumn="46" endline="6" loc="6.46 - 6.46"/></term><term lexeme="}" token="RIGHTCURL"><location begcolumn="5" begline="7" endcolumn="5" endline="7" loc="7.5 - 7.5"/></term><term lexeme="where" token="WHERE"><location begcolumn="5" begline="8" endcolumn="9" endline="8" loc="8.5 - 8.9"/></term><term lexeme="{" token="LEFTCURL"><location begcolumn="5" begline="9" endcolumn="5" endline="9" loc="9.5 - 9.5"/></term><term lexeme="fun" token="FUNCTION"><location begcolumn="7" begline="10" endcolumn="9" endline="10" loc="10.7 - 10.9"/></term><term lexeme="put" token="IDENTIFIER"><location begcolumn="11" begline="10" endcolumn="13" endline="10" loc="10.11 - 10.13"/></term><term lexeme="(" token="LEFTBRAC"><location begcolumn="14" begline="10" endcolumn="14" endline="10" loc="10.14 - 10.14"/></term><term lexeme="i" token="IDENTIFIER"><location begcolumn="15" begline="10" endcolumn="15" endline="10" loc="10.15 - 10.15"/></term><term lexeme=":" token="COL"><location begcolumn="16" begline="10" endcolumn="16" endline="10" loc="10.16 - 10.16"/></term><term lexeme="integer" token="INTEGER"><location begcolumn="17" begline="10" endcolumn="23" endline="10" loc="10.17 - 10.23"/></term><term lexeme=")" token="RIGHTBRAC"><location begcolumn="24" begline="10" endcolumn="24" endline="10" loc="10.24 - 10.24"/></term><term lexeme=":" token="COL"><location begcolumn="25" begline="10" endcolumn="25" endline="10" loc="10.25 - 10.25"/></term><term lexeme="void" token="VOID"><location begcolumn="26" begline="10" endcolumn="29" endline="10" loc="10.26 - 10.29"/></term><term lexeme="=" token="ASIGN"><location begcolumn="31" begline="10" endcolumn="31" endline="10" loc="10.31 - 10.31"/></term><term lexeme="{" token="LEFTCURL"><location begcolumn="11" begline="11" endcolumn="11" endline="11" loc="11.11 - 11.11"/></term><term lexeme="if" token="IF"><location begcolumn="13" begline="12" endcolumn="14" endline="12" loc="12.13 - 12.14"/></term><term lexeme="(" token="LEFTBRAC"><location begcolumn="16" begline="12" endcolumn="16" endline="12" loc="12.16 - 12.16"/></term><term lexeme="i" token="IDENTIFIER"><location begcolumn="17" begline="12" endcolumn="17" endline="12" loc="12.17 - 12.17"/></term><term lexeme="==" token="EQL"><location begcolumn="18" begline="12" endcolumn="19" endline="12" loc="12.18 - 12.19"/></term><term lexeme="0" token="INTCONST"><location begcolumn="20" begline="12" endcolumn="20" endline="12" loc="12.20 - 12.20"/></term><term lexeme=")" token="RIGHTBRAC"><location begcolumn="21" begline="12" endcolumn="21" endline="12" loc="12.21 - 12.21"/></term><term lexeme="then" token="THEN"><location begcolumn="23" begline="12" endcolumn="26" endline="12" loc="12.23 - 12.26"/></term><term lexeme="none" token="NONE"><location begcolumn="28" begline="12" endcolumn="31" endline="12" loc="12.28 - 12.31"/></term><term lexeme="else" token="ELSE"><location begcolumn="33" begline="12" endcolumn="36" endline="12" loc="12.33 - 12.36"/></term><term lexeme="{" token="LEFTCURL"><location begcolumn="38" begline="12" endcolumn="38" endline="12" loc="12.38 - 12.38"/></term><term lexeme="put" token="IDENTIFIER"><location begcolumn="15" begline="13" endcolumn="17" endline="13" loc="13.15 - 13.17"/></term><term lexeme="(" token="LEFTBRAC"><location begcolumn="18" begline="13" endcolumn="18" endline="13" loc="13.18 - 13.18"/></term><term lexeme="i" token="IDENTIFIER"><location begcolumn="19" begline="13" endcolumn="19" endline="13" loc="13.19 - 13.19"/></term><term lexeme="/" token="SLASH"><location begcolumn="20" begline="13" endcolumn="20" endline="13" loc="13.20 - 13.20"/></term><term lexeme="10" token="INTCONST"><location begcolumn="21" begline="13" endcolumn="22" endline="13" loc="13.21 - 13.22"/></term><term lexeme=")" token="RIGHTBRAC"><location begcolumn="23" begline="13" endcolumn="23" endline="13" loc="13.23 - 13.23"/></term><term lexeme=";" token="SEMCOL"><location begcolumn="24" begline="13" endcolumn="24" endline="13" loc="13.24 - 13.24"/></term><term lexeme="putChar" token="IDENTIFIER"><location begcolumn="15" begline="14" endcolumn="21" endline="14" loc="14.15 - 14.21"/></term><term lexeme="(" token="LEFTBRAC"><location begcolumn="22" begline="14" endcolumn="22" endline="14" loc="14.22 - 14.22"/></term><term lexeme="(" token="LEFTBRAC"><location begcolumn="23" begline="14" endcolumn="23" endline="14" loc="14.23 - 14.23"/></term><term lexeme="(" token="LEFTBRAC"><location begcolumn="24" begline="14" endcolumn="24" endline="14" loc="14.24 - 14.24"/></term><term lexeme="i" token="IDENTIFIER"><location begcolumn="25" begline="14" endcolumn="25" endline="14" loc="14.25 - 14.25"/></term><term lexeme="%" token="MOD"><location begcolumn="26" begline="14" endcolumn="26" endline="14" loc="14.26 - 14.26"/></term><term lexeme="10" token="INTCONST"><location begcolumn="27" begline="14" endcolumn="28" endline="14" loc="14.27 - 14.28"/></term><term lexeme="+" token="PLUS"><location begcolumn="29" begline="14" endcolumn="29" endline="14" loc="14.29 - 14.29"/></term><term lexeme="(" token="LEFTBRAC"><location begcolumn="30" begline="14" endcolumn="30" endline="14" loc="14.30 - 14.30"/></term><term lexeme="'0'" token="CHARACTERCONST"><location begcolumn="31" begline="14" endcolumn="33" endline="14" loc="14.31 - 14.33"/></term><term lexeme=":" token="COL"><location begcolumn="34" begline="14" endcolumn="34" endline="14" loc="14.34 - 14.34"/></term><term lexeme="integer" token="INTEGER"><location begcolumn="35" begline="14" endcolumn="41" endline="14" loc="14.35 - 14.41"/></term><term lexeme=")" token="RIGHTBRAC"><location begcolumn="42" begline="14" endcolumn="42" endline="14" loc="14.42 - 14.42"/></term><term lexeme=")" token="RIGHTBRAC"><location begcolumn="43" begline="14" endcolumn="43" endline="14" loc="14.43 - 14.43"/></term><term lexeme=":" token="COL"><location begcolumn="44" begline="14" endcolumn="44" endline="14" loc="14.44 - 14.44"/></term><term lexeme="char" token="CHAR"><location begcolumn="45" begline="14" endcolumn="48" endline="14" loc="14.45 - 14.48"/></term><term lexeme=")" token="RIGHTBRAC"><location begcolumn="49" begline="14" endcolumn="49" endline="14" loc="14.49 - 14.49"/></term><term lexeme=")" token="RIGHTBRAC"><location begcolumn="50" begline="14" endcolumn="50" endline="14" loc="14.50 - 14.50"/></term><term lexeme=";" token="SEMCOL"><location begcolumn="51" begline="14" endcolumn="51" endline="14" loc="14.51 - 14.51"/></term><term lexeme="}" token="RIGHTCURL"><location begcolumn="13" begline="15" endcolumn="13" endline="15" loc="15.13 - 15.13"/></term><term lexeme=";" token="SEMCOL"><location begcolumn="14" begline="15" endcolumn="14" endline="15" loc="15.14 - 15.14"/></term><term lexeme="}" token="RIGHTCURL"><location begcolumn="11" begline="16" endcolumn="11" endline="16" loc="16.11 - 16.11"/></term><term lexeme="}" token="RIGHTCURL"><location begcolumn="5" begline="17" endcolumn="5" endline="17" loc="17.5 - 17.5"/></term><term lexeme="var" token="VARIABLE"><location begcolumn="1" begline="18" endcolumn="3" endline="18" loc="18.1 - 18.3"/></term><term lexeme="j" token="IDENTIFIER"><location begcolumn="5" begline="18" endcolumn="5" endline="18" loc="18.5 - 18.5"/></term><term lexeme=":" token="COL"><location begcolumn="6" begline="18" endcolumn="6" endline="18" loc="18.6 - 18.6"/></term><term lexeme="^" token="CARET"><location begcolumn="8" begline="18" endcolumn="8" endline="18" loc="18.8 - 18.8"/></term><term lexeme="char" token="CHAR"><location begcolumn="9" begline="18" endcolumn="12" endline="18" loc="18.9 - 18.12"/></term><term lexeme="var" token="VARIABLE"><location begcolumn="1" begline="19" endcolumn="3" endline="19" loc="19.1 - 19.3"/></term><term lexeme="i" token="IDENTIFIER"><location begcolumn="5" begline="19" endcolumn="5" endline="19" loc="19.5 - 19.5"/></term><term lexeme=":" token="COL"><location begcolumn="6" begline="19" endcolumn="6" endline="19" loc="19.6 - 19.6"/></term><term lexeme="integer" token="INTEGER"><location begcolumn="8" begline="19" endcolumn="14" endline="19" loc="19.8 - 19.14"/></term><term lexeme="var" token="VARIABLE"><location begcolumn="1" begline="20" endcolumn="3" endline="20" loc="20.1 - 20.3"/></term><term lexeme="c" token="IDENTIFIER"><location begcolumn="5" begline="20" endcolumn="5" endline="20" loc="20.5 - 20.5"/></term><term lexeme=":" token="COL"><location begcolumn="6" begline="20" endcolumn="6" endline="20" loc="20.6 - 20.6"/></term><term lexeme="char" token="CHAR"><location begcolumn="7" begline="20" endcolumn="10" endline="20" loc="20.7 - 20.10"/></term><term lexeme="var" token="VARIABLE"><location begcolumn="1" begline="21" endcolumn="3" endline="21" loc="21.1 - 21.3"/></term><term lexeme="t" token="IDENTIFIER"><location begcolumn="5" begline="21" endcolumn="5" endline="21" loc="21.5 - 21.5"/></term><term lexeme=":" token="COL"><location begcolumn="7" begline="21" endcolumn="7" endline="21" loc="21.7 - 21.7"/></term><term lexeme="integer" token="INTEGER"><location begcolumn="8" begline="21" endcolumn="14" endline="21" loc="21.8 - 21.14"/></term><term lexeme="fun" token="FUNCTION"><location begcolumn="1" begline="22" endcolumn="3" endline="22" loc="22.1 - 22.3"/></term><term lexeme="main" token="IDENTIFIER"><location begcolumn="5" begline="22" endcolumn="8" endline="22" loc="22.5 - 22.8"/></term><term lexeme="(" token="LEFTBRAC"><location begcolumn="9" begline="22" endcolumn="9" endline="22" loc="22.9 - 22.9"/></term><term lexeme=")" token="RIGHTBRAC"><location begcolumn="10" begline="22" endcolumn="10" endline="22" loc="22.10 - 22.10"/></term><term lexeme=":" token="COL"><location begcolumn="11" begline="22" endcolumn="11" endline="22" loc="22.11 - 22.11"/></term><term lexeme="integer" token="INTEGER"><location begcolumn="12" begline="22" endcolumn="18" endline="22" loc="22.12 - 22.18"/></term><term lexeme="=" token="ASIGN"><location begcolumn="20" begline="22" endcolumn="20" endline="22" loc="22.20 - 22.20"/></term><term lexeme="{" token="LEFTCURL"><location begcolumn="5" begline="23" endcolumn="5" endline="23" loc="23.5 - 23.5"/></term><term lexeme="i" token="IDENTIFIER"><location begcolumn="7" begline="28" endcolumn="7" endline="28" loc="28.7 - 28.7"/></term><term lexeme="=" token="ASIGN"><location begcolumn="9" begline="28" endcolumn="9" endline="28" loc="28.9 - 28.9"/></term><term lexeme="test" token="IDENTIFIER"><location begcolumn="11" begline="28" endcolumn="14" endline="28" loc="28.11 - 28.14"/></term><term lexeme="(" token="LEFTBRAC"><location begcolumn="15" begline="28" endcolumn="15" endline="28" loc="28.15 - 28.15"/></term><term lexeme="0" token="INTCONST"><location begcolumn="16" begline="28" endcolumn="16" endline="28" loc="28.16 - 28.16"/></term><term lexeme=")" token="RIGHTBRAC"><location begcolumn="17" begline="28" endcolumn="17" endline="28" loc="28.17 - 28.17"/></term><term lexeme=";" token="SEMCOL"><location begcolumn="18" begline="28" endcolumn="18" endline="28" loc="28.18 - 28.18"/></term><term lexeme="putChar" token="IDENTIFIER"><location begcolumn="7" begline="31" endcolumn="13" endline="31" loc="31.7 - 31.13"/></term><term lexeme="(" token="LEFTBRAC"><location begcolumn="14" begline="31" endcolumn="14" endline="31" loc="31.14 - 31.14"/></term><term lexeme="'i'" token="CHARACTERCONST"><location begcolumn="15" begline="31" endcolumn="17" endline="31" loc="31.15 - 31.17"/></term><term lexeme=")" token="RIGHTBRAC"><location begcolumn="18" begline="31" endcolumn="18" endline="31" loc="31.18 - 31.18"/></term><term lexeme=";" token="SEMCOL"><location begcolumn="19" begline="31" endcolumn="19" endline="31" loc="31.19 - 31.19"/></term><term lexeme="putInteger" token="IDENTIFIER"><location begcolumn="7" begline="32" endcolumn="16" endline="32" loc="32.7 - 32.16"/></term><term lexeme="(" token="LEFTBRAC"><location begcolumn="17" begline="32" endcolumn="17" endline="32" loc="32.17 - 32.17"/></term><term lexeme="i" token="IDENTIFIER"><location begcolumn="18" begline="32" endcolumn="18" endline="32" loc="32.18 - 32.18"/></term><term lexeme=")" token="RIGHTBRAC"><location begcolumn="19" begline="32" endcolumn="19" endline="32" loc="32.19 - 32.19"/></term><term lexeme=";" token="SEMCOL"><location begcolumn="20" begline="32" endcolumn="20" endline="32" loc="32.20 - 32.20"/></term><term lexeme="0" token="INTCONST"><location begcolumn="7" begline="41" endcolumn="7" endline="41" loc="41.7 - 41.7"/></term><term lexeme=";" token="SEMCOL"><location begcolumn="8" begline="41" endcolumn="8" endline="41" loc="41.8 - 41.8"/></term><term lexeme="}" token="RIGHTCURL"><location begcolumn="5" begline="42" endcolumn="5" endline="42" loc="42.5 - 42.5"/></term><term lexeme="where" token="WHERE"><location begcolumn="7" begline="42" endcolumn="11" endline="42" loc="42.7 - 42.11"/></term><term lexeme="{" token="LEFTCURL"><location begcolumn="13" begline="42" endcolumn="13" endline="42" loc="42.13 - 42.13"/></term><term lexeme="fun" token="FUNCTION"><location begcolumn="7" begline="44" endcolumn="9" endline="44" loc="44.7 - 44.9"/></term><term lexeme="test" token="IDENTIFIER"><location begcolumn="11" begline="44" endcolumn="14" endline="44" loc="44.11 - 44.14"/></term><term lexeme="(" token="LEFTBRAC"><location begcolumn="15" begline="44" endcolumn="15" endline="44" loc="44.15 - 44.15"/></term><term lexeme="s" token="IDENTIFIER"><location begcolumn="16" begline="44" endcolumn="16" endline="44" loc="44.16 - 44.16"/></term><term lexeme=":" token="COL"><location begcolumn="17" begline="44" endcolumn="17" endline="44" loc="44.17 - 44.17"/></term><term lexeme="integer" token="INTEGER"><location begcolumn="18" begline="44" endcolumn="24" endline="44" loc="44.18 - 44.24"/></term><term lexeme=")" token="RIGHTBRAC"><location begcolumn="25" begline="44" endcolumn="25" endline="44" loc="44.25 - 44.25"/></term><term lexeme=":" token="COL"><location begcolumn="26" begline="44" endcolumn="26" endline="44" loc="44.26 - 44.26"/></term><term lexeme="integer" token="INTEGER"><location begcolumn="27" begline="44" endcolumn="33" endline="44" loc="44.27 - 44.33"/></term><term lexeme="=" token="ASIGN"><location begcolumn="35" begline="44" endcolumn="35" endline="44" loc="44.35 - 44.35"/></term><term lexeme="{" token="LEFTCURL"><location begcolumn="37" begline="44" endcolumn="37" endline="44" loc="44.37 - 44.37"/></term><term lexeme="while" token="WHILE"><location begcolumn="9" begline="46" endcolumn="13" endline="46" loc="46.9 - 46.13"/></term><term lexeme="(" token="LEFTBRAC"><location begcolumn="14" begline="46" endcolumn="14" endline="46" loc="46.14 - 46.14"/></term><term lexeme="s" token="IDENTIFIER"><location begcolumn="15" begline="46" endcolumn="15" endline="46" loc="46.15 - 46.15"/></term><term lexeme="&lt;" token="LT"><location begcolumn="16" begline="46" endcolumn="16" endline="46" loc="46.16 - 46.16"/></term><term lexeme="10" token="INTCONST"><location begcolumn="17" begline="46" endcolumn="18" endline="46" loc="46.17 - 46.18"/></term><term lexeme=")" token="RIGHTBRAC"><location begcolumn="19" begline="46" endcolumn="19" endline="46" loc="46.19 - 46.19"/></term><term lexeme="do" token="DO"><location begcolumn="21" begline="46" endcolumn="22" endline="46" loc="46.21 - 46.22"/></term><term lexeme="{" token="LEFTCURL"><location begcolumn="24" begline="46" endcolumn="24" endline="46" loc="46.24 - 46.24"/></term><term lexeme="s" token="IDENTIFIER"><location begcolumn="11" begline="48" endcolumn="11" endline="48" loc="48.11 - 48.11"/></term><term lexeme="=" token="ASIGN"><location begcolumn="12" begline="48" endcolumn="12" endline="48" loc="48.12 - 48.12"/></term><term lexeme="s" token="IDENTIFIER"><location begcolumn="13" begline="48" endcolumn="13" endline="48" loc="48.13 - 48.13"/></term><term lexeme="+" token="PLUS"><location begcolumn="14" begline="48" endcolumn="14" endline="48" loc="48.14 - 48.14"/></term><term lexeme="1" token="INTCONST"><location begcolumn="15" begline="48" endcolumn="15" endline="48" loc="48.15 - 48.15"/></term><term lexeme=";" token="SEMCOL"><location begcolumn="16" begline="48" endcolumn="16" endline="48" loc="48.16 - 48.16"/></term><term lexeme="putInteger" token="IDENTIFIER"><location begcolumn="11" begline="49" endcolumn="20" endline="49" loc="49.11 - 49.20"/></term><term lexeme="(" token="LEFTBRAC"><location begcolumn="21" begline="49" endcolumn="21" endline="49" loc="49.21 - 49.21"/></term><term lexeme="s" token="IDENTIFIER"><location begcolumn="22" begline="49" endcolumn="22" endline="49" loc="49.22 - 49.22"/></term><term lexeme=")" token="RIGHTBRAC"><location begcolumn="23" begline="49" endcolumn="23" endline="49" loc="49.23 - 49.23"/></term><term lexeme=";" token="SEMCOL"><location begcolumn="24" begline="49" endcolumn="24" endline="49" loc="49.24 - 49.24"/></term><term lexeme="}" token="RIGHTCURL"><location begcolumn="9" begline="50" endcolumn="9" endline="50" loc="50.9 - 50.9"/></term><term lexeme=";" token="SEMCOL"><location begcolumn="10" begline="50" endcolumn="10" endline="50" loc="50.10 - 50.10"/></term><term lexeme="s" token="IDENTIFIER"><location begcolumn="9" begline="52" endcolumn="9" endline="52" loc="52.9 - 52.9"/></term><term lexeme=";" token="SEMCOL"><location begcolumn="10" begline="52" endcolumn="10" endline="52" loc="52.10 - 52.10"/></term><term lexeme="}" token="RIGHTCURL"><location begcolumn="7" begline="53" endcolumn="7" endline="53" loc="53.7 - 53.7"/></term><term lexeme="where" token="WHERE"><location begcolumn="9" begline="53" endcolumn="13" endline="53" loc="53.9 - 53.13"/></term><term lexeme="{" token="LEFTCURL"><location begcolumn="15" begline="53" endcolumn="15" endline="53" loc="53.15 - 53.15"/></term><term lexeme="var" token="VARIABLE"><location begcolumn="9" begline="54" endcolumn="11" endline="54" loc="54.9 - 54.11"/></term><term lexeme="n" token="IDENTIFIER"><location begcolumn="13" begline="54" endcolumn="13" endline="54" loc="54.13 - 54.13"/></term><term lexeme=":" token="COL"><location begcolumn="14" begline="54" endcolumn="14" endline="54" loc="54.14 - 54.14"/></term><term lexeme="integer" token="INTEGER"><location begcolumn="15" begline="54" endcolumn="21" endline="54" loc="54.15 - 54.21"/></term><term lexeme="}" token="RIGHTCURL"><location begcolumn="7" begline="55" endcolumn="7" endline="55" loc="55.7 - 55.7"/></term><term lexeme="}" token="RIGHTCURL"><location begcolumn="5" begline="56" endcolumn="5" endline="56" loc="56.5 - 56.5"/></term><term lexeme="" token="EOF"/></lexan>